trading_core/__init__.py
trading_core/connector/kafka/KafkaConnector.py
trading_core/connector/postgres/PostgresqlDBConnector.py
trading_core/connector/postgres/__init__.py
trading_core/models/__init__.py
trading_core/models/initial_db.py
trading_core/models/binance/__init__.py
trading_core/models/binance/data/BinanceFutureCOINMExchangeInfoSymbol.py
trading_core/models/binance/data/BinanceFutureUSDTExchangeInfoSymbol.py
trading_core/models/binance/data/BinanceSpotExchangeInfoSymbol.py
trading_core/models/binance/data/__init__.py
trading_core/models/binance/data/base.py
trading_core/models/binance/stream/BinanceStreamFuturesCOINMKline.py
trading_core/models/binance/stream/BinanceStreamFuturesCOINMMarkPriceUpdate.py
trading_core/models/binance/stream/BinanceStreamFuturesUSDTKline.py
trading_core/models/binance/stream/BinanceStreamFuturesUSDTMarkPriceUpdate.py
trading_core/models/binance/stream/BinanceStreamSpotKline.py
trading_core/models/binance/stream/__init__.py
trading_core/models/binance/stream/base.py
trading_core/tests/__init__.py
trading_core/tests/test_models_binance_data_BinanceFutureCOINMExchangeInfoSymbol.py
trading_core/tests/test_models_binance_data_BinanceFutureUSDTExchangeInfoSymbol.py
trading_core/tests/test_models_binance_data_BinanceSpotExchangeInfoSymbol.py
trading_core/tests/test_models_binance_stream_BinanceStreamFuturesCOINMKline.py
trading_core/tests/test_models_binance_stream_BinanceStreamFuturesCOINMMarkPriceUpdate.py
trading_core/tests/test_models_binance_stream_BinanceStreamFuturesUSDTKline.py
trading_core/tests/test_models_binance_stream_BinanceStreamFuturesUSDTMarkPriceUpdate.py
trading_core/tests/test_models_binance_stream_BinanceStreamSpotKline.py
trading_core/utilities/LoadJsonConfig.py
trading_core-0.1.8.dist-info/METADATA
trading_core-0.1.8.dist-info/WHEEL
trading_core-0.1.8.dist-info/top_level.txt
trading_core-0.1.8.dist-info/RECORD
