Metadata-Version: 2.4
Name: trading-core
Version: 0.1.8
Summary: Trading data platform core library (Kafka + Postgres + Binance)
Author-email: Kiw Comp <kiw.share.resource@gmail.com>
License: MIT
Requires-Python: >=3.12
Requires-Dist: sqlalchemy==2.0.43
Requires-Dist: psycopg2-binary==2.9.10
Requires-Dist: pydantic==2.11.7
Requires-Dist: kafka-python==2.2.15
Requires-Dist: confluent-kafka
Requires-Dist: requests==2.32.5
Requires-Dist: websockets==15.0.1
